Makefile
README.md
ampule_config.mk
setup.cfg
setup.py
ampule/__init__.py
ampule/ampule.py
ampule.egg-info/PKG-INFO
ampule.egg-info/SOURCES.txt
ampule.egg-info/dependency_links.txt
ampule.egg-info/requires.txt
ampule.egg-info/top_level.txt
dat/poly.dat
dat/hermite/H_0.dat
dat/hermite/H_1.dat
dat/hermite/H_2.dat
dat/hermite/H_3.dat
dat/hermite/H_4.dat
figs/py/hermite.py
figs/py/poly.py