Metadata-Version: 1.1
Name: ampule
Version: 0.9.6
Summary: Ampule (Automated MatPlotLib) is a minimalistic tool designed for repeatednon-interactive processing and plotting of tabular data
Home-page: https://github.com/Toucandy/ampule
Author: Ilya Pershin
Author-email: pershin2010@gmail.com
License: MIT
Download-URL: https://github.com/Toucandy/ampule/archive/v_096.tar.gz
Keywords: matplotlib,plotting,pandas
Platform: UNKNOWN
Classifier: Development Status :: 4 - Beta
Classifier: Intended Audience :: Science/Research
Classifier: Topic :: Scientific/Engineering :: Information Analysis
Classifier: License :: OSI Approved :: MIT License
Classifier: Programming Language :: Python :: 3
